unique_randomizer/__init__.py
unique_randomizer/stochastic_beam_search.py
unique_randomizer/stochastic_beam_search_test.py
unique_randomizer/unique_randomizer.py
unique_randomizer/unique_randomizer_simple.py
unique_randomizer/unique_randomizer_simple_test.py
unique_randomizer/unique_randomizer_test.py
unique_randomizer/estimation/__init__.py
unique_randomizer/estimation/create_plots.py
unique_randomizer/estimation/hindsight_gumbel_estimation.py
unique_randomizer/tsp/__init__.py
unique_randomizer/tsp/tsp.py
unique_randomizer-0.0.1.dist-info/LICENSE
unique_randomizer-0.0.1.dist-info/METADATA
unique_randomizer-0.0.1.dist-info/WHEEL
unique_randomizer-0.0.1.dist-info/top_level.txt
unique_randomizer-0.0.1.dist-info/RECORD
