Metadata-Version: 2.1
Name: unique-randomizer
Version: 0.0.1
Summary: UniqueRandomizer: Incremental Sampling Without Replacement
Home-page: https://github.com/google-research/unique-randomizer
Author: Google LLC
Author-email: no-reply@google.com
License: UNKNOWN
Keywords: unique randomizer UniqueRandomizer incremental sampling without replacement sequence models
Platform: UNKNOWN
Classifier: Intended Audience :: Developers
Classifier: Intended Audience :: Science/Research
Classifier: License :: OSI Approved :: Apache Software License
Classifier: Operating System :: OS Independent
Classifier: Programming Language :: Python :: 3
Classifier: Programming Language :: Python :: 3.6
Classifier: Programming Language :: Python :: 3.7
Classifier: Programming Language :: Python :: 3.8
Classifier: Topic :: Scientific/Engineering
Classifier: Topic :: Scientific/Engineering :: Mathematics
Classifier: Topic :: Scientific/Engineering :: Artificial Intelligence
Classifier: Topic :: Software Development
Classifier: Topic :: Software Development :: Libraries
Classifier: Topic :: Software Development :: Libraries :: Python Modules
Requires-Python: >=3
Requires-Dist: absl-py (>=0.6.1)
Requires-Dist: numpy (>=1.15.4)
Requires-Dist: scipy (>=1.1.0)
